interface
django_query_signals
