Metadata-Version: 1.1
Name: django-query-signals
Version: 0.0.2
Summary: Django Query Signals
Home-page: https://repository.example.com/django-query-signals/
Author: Martin P. Hellwig
Author-email: martin.hellwig@gmail.com
License: BSD
Download-URL: https://repository.example.com/django-query-signals/download/0.0.2.zip
Keywords: django,django-integrator
Platform: UNKNOWN
Classifier: Programming Language :: Python :: 3
